{
   "feed": {
      "category": [
         {
            "scheme": "urn:ietf:params:rolie:category:information-type",
            "term": "csaf"
         }
      ],
      "entry": [
         {
            "content": {
               "src": "https://raw.githubusercontent.com/cisagov/CSAF/develop/csaf_files/IT/white/2024/va-24-262-01.json",
               "type": "application/json"
            },
            "format": {
               "schema": "https://docs.oasis-open.org/csaf/csaf/v2.0/csaf_json_schema.json",
               "version": "2.0"
            },
            "id": "VA-24-262-01",
            "link": [
               {
                  "href": "https://raw.githubusercontent.com/cisagov/CSAF/develop/csaf_files/IT/white/2024/va-24-262-01.json",
                  "rel": "self"
               },
               {
                  "href": "https://raw.githubusercontent.com/cisagov/CSAF/develop/csaf_files/IT/white/2024/va-24-262-01.json.sha512",
                  "ref": "hash"
               },
               {
                  "href": "https://raw.githubusercontent.com/cisagov/CSAF/develop/csaf_files/IT/white/2024/va-24-262-01.json.asc",
                  "ref": "signature"
               }
            ],
            "published": "2024-09-18T15:26:00",
            "summary": {
               "content": "The Planet Fitness Workouts iOS and Android mobile apps are vulnerable to network attacks due to improper TLS certificate validation, allowing an attacker to obtain session tokens and sensitive information. This issue was fixed in version 9.8.12."
            },
            "title": "Planet Fitness Workouts mobile apps do not properly validate TLS certificates",
            "updated": "2024-09-18T16:56:00"
         },
         {
            "content": {
               "src": "https://raw.githubusercontent.com/cisagov/CSAF/develop/csaf_files/IT/white/2024/va-24-201-01.json",
               "type": "application/json"
            },
            "format": {
               "schema": "https://docs.oasis-open.org/csaf/csaf/v2.0/csaf_json_schema.json",
               "version": "2.0"
            },
            "id": "VA-24-201-01",
            "link": [
               {
                  "href": "https://raw.githubusercontent.com/cisagov/CSAF/develop/csaf_files/IT/white/2024/va-24-201-01.json",
                  "rel": "self"
               },
               {
                  "href": "https://raw.githubusercontent.com/cisagov/CSAF/develop/csaf_files/IT/white/2024/va-24-201-01.json.sha512",
                  "ref": "hash"
               },
               {
                  "href": "https://raw.githubusercontent.com/cisagov/CSAF/develop/csaf_files/IT/white/2024/va-24-201-01.json.asc",
                  "ref": "signature"
               }
            ],
            "published": "2024-07-19T16:00:00",
            "summary": {
               "content": "Adminer and AdminerEvo contain multiple vulnerabilities. Successful exploitation of these vulnerabilities could allow a remote, unauthenticated attacker to deny service, enumerate and access systems indirectly, upload arbitrary files, and execute arbitrary code. Adminer is no longer maintained. All of these vulnerabilities are fixed in AdminerEvo 4.8.4."
            },
            "title": "Adminer and AdminerEvo Multiple Vulnerabilities",
            "updated": "2024-09-18T16:00:00"
         },
         {
            "content": {
               "src": "https://raw.githubusercontent.com/cisagov/CSAF/develop/csaf_files/IT/white/2024/va-24-254-01.json",
               "type": "application/json"
            },
            "format": {
               "schema": "https://docs.oasis-open.org/csaf/csaf/v2.0/csaf_json_schema.json",
               "version": "2.0"
            },
            "id": "VA-24-254-01",
            "link": [
               {
                  "href": "https://raw.githubusercontent.com/cisagov/CSAF/develop/csaf_files/IT/white/2024/va-24-254-01.json",
                  "rel": "self"
               },
               {
                  "href": "https://raw.githubusercontent.com/cisagov/CSAF/develop/csaf_files/IT/white/2024/va-24-254-01.json.sha512",
                  "ref": "hash"
               },
               {
                  "href": "https://raw.githubusercontent.com/cisagov/CSAF/develop/csaf_files/IT/white/2024/va-24-254-01.json.asc",
                  "ref": "signature"
               }
            ],
            "published": "2024-09-10T20:08:00",
            "summary": {
               "content": "IBM webMethods Integration contains multiple vulnerabilities that could allow an authenticated attacker to escalate privileges within webMethods, execute arbitrary operating system commands, or read arbitrary files."
            },
            "title": "IBM webMethods Integration Multiple Vulnerabilities",
            "updated": "2024-09-10T20:08:00"
         },
         {
            "content": {
               "src": "https://raw.githubusercontent.com/cisagov/CSAF/develop/csaf_files/IT/white/2024/va-24-254-02.json",
               "type": "application/json"
            },
            "format": {
               "schema" : "https://docs.oasis-open.org/csaf/csaf/v2.0/csaf_json_schema.json",
               "version" : "2.0"
            },
            "id": "VA-24-254-02",
            "link": [
               {
                  "href": "https://raw.githubusercontent.com/cisagov/CSAF/develop/csaf_files/IT/white/2024/va-24-254-02.json",
                  "rel": "self"
               },
               {
                  "href": "https://raw.githubusercontent.com/cisagov/CSAF/develop/csaf_files/IT/white/2024/va-24-254-02.json.sha512",
                  "ref": "hash"
               },
               {
                  "href": "https://raw.githubusercontent.com/cisagov/CSAF/develop/csaf_files/IT/white/2024/va-24-254-02.json.asc",
                  "ref": "signature"
               }
            ],
            "published": "2024-09-10T16:03:00",
            "summary": {
               "content: "TopQuadrant TopBraid EDG stores credentials for external services insecurely and processes untrusted XML entities. An authenticated attacker could obtain credentials for remote services, read local files, or access URLs."
            },
            "title": "TopQuadrant TopBraid EDG Insecure External Password Storage and XXE Vulnerabilities",
            "updated": "2024-09-10T16:03:00"
         }
      ],
      "id": "cisa-csaf-it-feed-tlp-white",
      "link": [
         {
            "href": "https://raw.githubusercontent.com/cisagov/CSAF/develop/csaf_files/IT/white/cisa-csaf-it-feed-tlp-white.json",
            "rel": "self"
         }
      ],
      "title": "CISA CSAF IT feed (TLP:WHITE)",
      "updated": "2024-09-27T15:29:01"
   }
}
